symmetricjsonrpc3/__init__.py
symmetricjsonrpc3/dispatcher.py
symmetricjsonrpc3/io.py
symmetricjsonrpc3/json.py
symmetricjsonrpc3/rpc.py
symmetricjsonrpc3-0.5.1.dist-info/COPYING
symmetricjsonrpc3-0.5.1.dist-info/COPYING.LESSER
symmetricjsonrpc3-0.5.1.dist-info/METADATA
symmetricjsonrpc3-0.5.1.dist-info/WHEEL
symmetricjsonrpc3-0.5.1.dist-info/top_level.txt
symmetricjsonrpc3-0.5.1.dist-info/RECORD
