Metadata-Version: 2.1
Name: symmetricjsonrpc3
Version: 0.5.1
Summary: A symmetric, transport-layer agnostic JSON RPC.
Author-email: Egil Moeller <redhog@redhog.org>, Nicklas Lindgren <nili@gulmohar.se>, "Robert \"Robikz\" Zalewski" <zalewapl@gmail.com>
Maintainer-email: "Robert \"Robikz\" Zalewski" <zalewapl@gmail.com>
Project-URL: Source, https://github.com/Zalewa/python-symmetricjsonrpc3
Project-URL: Changelog, https://github.com/Zalewa/python-symmetricjsonrpc3/blob/master/CHANGELOG.md
Classifier: Development Status :: 3 - Alpha
Classifier: Intended Audience :: Developers
Classifier: License :: OSI Approved :: GNU Lesser General Public License v2 or later (LGPLv2+)
Classifier: Programming Language :: Python :: 3
Classifier: Topic :: Software Development :: Libraries
Classifier: Topic :: System :: Networking
Requires-Python: >=3.8.1
License-File: COPYING
License-File: COPYING.LESSER
